Codegen/__init__.py
Codegen/codegen.py
Lexer/__init__.py
Lexer/laxer.py
Lexer/token.py
Parser/__init__.py
Parser/astNode.py
Parser/parser.py
Utils/__init__.py
Utils/constants.py
Utils/keywords.py
Utils/tokens.py
bhauRunner/__init__.py
bhauRunner/bhauRunner.py
BhauLang-0.3.dist-info/METADATA
BhauLang-0.3.dist-info/WHEEL
BhauLang-0.3.dist-info/entry_points.txt
BhauLang-0.3.dist-info/top_level.txt
BhauLang-0.3.dist-info/RECORD
