Metadata-Version: 2.1
Name: BhauLang
Version: 0.3
